snitchvis/__init__.py
snitchvis/clock.py
snitchvis/controls.py
snitchvis/frame_renderer.py
snitchvis/interface.py
snitchvis/renderer.py
snitchvis/utils.py
snitchvis/version.py
snitchvis/visualizer.py
snitchvis/widgets.py
snitchvis/resources/clipboard.svg
snitchvis/resources/frame_back.png
snitchvis/resources/frame_next.png
snitchvis/resources/info.png
snitchvis/resources/pause.png
snitchvis/resources/play.png
snitchvis/resources/play_normal.png
snitchvis/resources/play_reverse.png
snitchvis/resources/settings_wheel.png
snitchvis/resources/speed_down.png
snitchvis/resources/speed_up.png
snitchvis/resources/world.png
snitchvis-1.0.0.dist-info/METADATA
snitchvis-1.0.0.dist-info/WHEEL
snitchvis-1.0.0.dist-info/top_level.txt
snitchvis-1.0.0.dist-info/RECORD
