Metadata-Version: 2.1
Name: snitchvis
Version: 1.0.0
Requires-Dist: numpy
Requires-Dist: PyQt6
